{
  "source_id": "civ-33",
  "title": "Civilization #33: The Rise and Fall of the Byzantine Empire",
  "part_id": "",
  "part": {},
  "review_status": "source_reviewed",
  "transcript_status": "curated_transcript",
  "source_video": "https://www.youtube.com/watch?v=abs6z7VPEMc",
  "route": null,
  "opening": "okay so good morning um today this\nmorning we are doing the bantine Empire\nand I will be looking at three questions\nthe first question is why do we have the\nbantin\nEmpire um historically we have",
  "sections": [
    {
      "slug": "byzantine-roman-continuation",
      "label": "Byzantine Roman Continuation",
      "body": "seen the Byzantine Empire as a\ncontinuation of the Roman Empire we have\nthe bisan Empire because Constantine the\nGreat in 330\num transfer the capital of the Roman\nEmpire from Rome to banum which later\nbecame which which he called New Rome\nand which eventually was renamed to\nconstantinopole so why did he make that\ntransition okay that's the first\nquestion second question\nis how did the ban Empire rise it fell\nit lasted\nfrom um 3:30 until 1453 when the aroman\nTurks\noverran the uh capital of Constantinople\nso it lasted for over a thousand years\narguably it is the most enduring World\nEmpire in human history so how was it so\nsuccessful that's that's the second\nquestion and the third and last question\nis why did It ultimately ultimately\ndecline why did it collapse what were\nthe factors Le that led to its eventual\ndemise okay so those are the three\nquestions we will we will be looking at\num this morning and what I want to do\nfirst",
      "claim_numbers": [
        1
      ]
    },
    {
      "slug": "scholarly-consensus-first",
      "label": "Scholarly Consensus First",
      "body": "I want to present the scholarly\nconsensus what is generally accepted\nwhat is generally believed about these\nthree questions and then I want to\npresent my own perspective um in order\nto uh refute the scholar consensus all\nright so let's start um this is the\nRoman Empire in 117\nand as you can see it is huge it it\nspans across the\nMediterranean uh this is Spain over here\nis\num\nAnatolia Egypt the lant okay so it is a\nhuge World Empire and that's a problem\nit's just much too big um unlike China\num it has no natural boundaries and\nthroughout most of its history history\nit uh was invaded by barbarians what\nwhat the Romans call barbarians\nbasically these Germanic Gothic tribes\nfrom the north it also had a major\nadversary in the Persian Empire uh at\nthis time they were fighting against the\nparThebans uh but later on they would\nfight against what is what we call the\nsassanian Persian\nEmpire um and so this was not a really\nsustainable Empire internally as we\ndiscussed last class there was a\ncontradiction they were an Empire but\nthey believed themselves to be Republic\nit was important for them to maintain\nRepublican institutions like the Senate\neven though um it was to the detriment\nof the management of the Empire what I\nmean by that is that throughout this\ntime on paper in Theory it was committee\nit was ruled by committee okay the\nSenate was really in command and as we\ndiscussed in previous classes the Senate\nis composed of the Roman aristocracy the\nruling houses of Rome when you have that\nwhen you have committee uh rule by\ncommittee um when Powers divide up\nevenly among the ruling houses of an\nEmpire the only thing they can really\nagree on is to be corrupt together and\nand so the Senate was a huge problem\nbecause they basically monopolized\nwealth and there was a lot discontent in\nthe provinces there was a lot of\nDisconnect among the people and the\nRomans tried different solutions to\nthis um but none other Solutions\nworked and in and eventually we had\nsomething called the third Century\ncrisis the crisis of the third Century\nwhich basically meant the Roman Empire\nwas about to disintegrate there were\ncivil wars going on uh there were these\ninvasions from the north uh there was\neconomic collapse there's a plague so in\nthe 3rd\nCentury um there it really seemed the\nRoman Empire was on a brink of complete\nimplosion then a military genius by name\nof uh Diocletian he re reunit the Empire\nand he recognized\nwe basically needed to change the system\nand we needed to make radical changes in\norder to save the Roman Empire\nokay um as you can see it is extremely\ndifficult to protect Rome against um the\nBarbarian Invaders over time eventually\nthe Western portion of the Empire will\nbe overrun by uh these barbarians who we\ncall the germanics the Goths the Slavs\nthe Hunts okay basically these are the\nsuccessors to the yamai people and they\ncome from the steps so they are\nextremely\naggressive uh mobile people um who will\neventually overrun the Roman Empire and\nthey will\nestablish um basically the tribes that\nwill eventually give us the modern\nstates of\nGermany um Britain France okay so\nbasically these are the ancestors of\nWestern Europeans all\nright\num as um so as you can see\nthese um barbarians they will\nestablished their own Empires and all\nthat we left after year about the year\n500 is the Eastern Roman Empire which is\nthe\nsuccessor uh to the uh Roman Empire okay\nand um even though they can call him\nRomans and they identify themselves as\nRomans historians refer to to the to the\nEastern Roman Empire as the byzantines\nokay they they again they did they\nthemselves did not call themselves The\nbantin byzantines it's what later\nhistorians call them okay so the man who\nmakes this transition uh who basically\nis a founder of the ban Empire his name\nis Constantine the Great and what he\ndoes that's very important is that he\nshifts cap Capal from Rome to banum on\nthe\nBosphorus and today we call this place\nconapo it's still there guys if you want\nto visit it's called Istanbul in in in\nturkey and it's a beautiful city uh\ndefinitely one of the most beautiful\ncities in the world now the question is\nsorry uh I skipped the question then is\nwhy was this move make and what modern\nhistorians uh believe is that this was a\nstrategic\ndecision um first of all Rome was not\neasily defended so it's very common\nthroughout its history for it to be\noverrun by provincial military Governor\nokay so think of Julius Caesar but also\nthere were others as well who did the\nsame thing who were extremely successful\nin the provinces and they took the\nmilitary and conquered Rome it was very\neasy to overrun Rome and then declare\nhimself uh Emperor so by moving into\nConstantinople um he the city the\ncapital is now imprintable okay it is\nimpossible to besiege uh it is easily\ndefensible and how so I will show you\nlater on okay the other thing that's\nreally important about this transition\nis conol is really at the center of the\nEmpire now Rome was too far to the west\nand most of um the Roman her's most\nwealthy provinces the most important\nProvince like Egypt Anatolia and the\nlavant were actually in the East okay so\nit's recognition the fact the center of\ngravity um in the empire was really in\nthe East and the third reason is again\nthroughout most of its history Rome's\nmain competitor were the Persian Empire\nto the East and so by moving to Conant\npole it allows the emperor to most\neasily and most directly respond to the\nthreat of the Persians okay so this is\nthe scholarly consensus okay um but as I\nwill show you later on I disagree with\nthis consensus I think there was a much\nmore important reason why Constantine\nmade this move okay\num the ban Empire becomes this the um\nbirth place of modern Christianity okay\nConstantine the Great is the first\nChristian Roman Empire Emperor he\nconverts to Christianity but not only\nthat but he lays the intellectual basis\nfor Mar Christianity for something call\nthe Council of Nikia niia the\npronunciation is different okay it's\nproperly pronounced Nikia but most\npeople pronounce it NAA okay so the\nCouncil of NAA we talked about this last\nsemester where the Council of NAA was\nestablished to answer uh a theological\ndebate in the Christian world what is\nthe nature of Jesus what is relationship\nwith God as we discussed uh one more\npopular interpretations explanations is\nthe idea of arianism where Jesus is a\nless Divinity to God the Council of",
      "claim_numbers": [
        2
      ]
    },
    {
      "slug": "nicaea-trinity",
      "label": "Nicaea Trinity",
      "body": "Nicaea Nakia established the idea of the\nHoly Trinity which is that God Jesus and\nholy spirit are are co-equal they are\nseparate but they are co-equal we call\nthis the Holy Trinity the godhead okay\nso that is conant's major\ncontribution um after Constantine one of\nhis successors\ntheodosius makes Christianity the\nofficial religion of the Roman Empire\nthere's now a Crackdown on both the idea\nof paganism which used to be the\nreligion of the Roman Empire as well as\nthe ideaa of heresy okay especially the\nidea of\nirism um he also built something called",
      "claim_numbers": [
        4
      ]
    },
    {
      "slug": "theodosian-walls",
      "label": "Theodosian Walls",
      "body": "the Theodosian walls which makes Conant\nbasically impenetrable okay it makes it\na impenetrable Fortress and allows it U\nConant to stand for a thousand years\nokay as you can see from the F Theodosian\nwalls um it's huge okay this is just a\nperson you can see that there are two\nwalls there's a m protecting it um so\nfor about a thousand years these walls\nprotected the city there were that many\nsoldiers from the city you didn't\nactually need that many soldiers to\nprotect against\nInvaders the other thing so uh these\nwalls are still standing today you can\nactually go get on a plane fly to\nIstanbul and visit these walls okay they\nwere they were basically designed to\nstand for all eternity and that was the\nidea of constantinopole the Eternal City\nokay um they also had seaw walls so not\nonly could you not attack conable from\nby land you couldn't even attack it by\nsea one of the Great\nInventions um of constant pole is the\nidea of Greek Fire okay the story is\nthat um they were being attacked by the\nMuslims this is in the 8th century when\nuh the Muslims are expanding throughout\nthe world they're conquering uh both the\nSass sassanian Empire as well as the uh\nRoman Empire and they want to obviously\noverrun kopol and and ultimately what\nsaves the city is the invention of some\ncalled quick fire which is basically\nkerosene right you take kerosene you\nthrow it at someone and then the boat um\nis light on fire and the story is that\nthis was invented by a heniz Jew who\nconverted ity and he he has this great\nidea and then he approaches the emperor\nwith this uh invention and the emperor\nbelieves that he is an angel sent by God\nto save the city okay and so it is\nimpossible to actually launch a naval\nExpedition against cono because they'll\njust burn down your\nships\nokay um at the height of the bintine\nEmpire it almost reestablish lishes\nreconstitutes the entire Roman uh Empire\nand this is the year 565 at this point\nthe emperor is Justinian and at this\npoint the one who is leading the\nmilitary of the byzantines his name is\nBelisarius and he's considered the last\ngreat Roman general okay his military\ngenius is on par with that of Julius\nCaesar Hannibal all the great generals\nand through his military conquest but\nthe bising Empire ex um is able to\nexpand its influence but as we learned\nin this class once you reach a peak of\nEmpire there are problems okay so the\nfirst problem is that your city becomes\noverpopulated and when your city becomes\noverpopulated it becomes suceptible to\nthe plague okay so there's something\ncalled the justan plagu which wiped out\nanywhere between 50 to 60% of the entire\npopulation of Constantinople\nat this point uh the popul population of\nthe city is about 500,000 half a million\nthe plague killed 300,000 people that's\na lot of people okay even today Scholars\ndebate where this plague came from or\noriginally we belied it came from grain\nships from Egypt right because conol\nImports all its food from Egypt and so\nthere were Rats on these ships and these\nrats spread basically the bonic plague\nnow historians believe that actually\ncame from the steps the Hunts and\nthrough their Invasion okay so we don't\nknow what happened we just know uh we\njust know it killed a lot of people and\nthis greatly uh reduced the power of uh\nthe Empire also when you have these mil\nmilitary conquests you\noverextended okay so it is very\ndifficult to maintain this Empire and\nthe third problem is that that whenever\nthere's a military expansion the Empire\nthe emperor comes in conflict with the\ngeneral so even those Justinian and\nmilit serious they were great friends\ntheir wives were great friends they\nthemselves had a lot of personal\nconflict in fact um towards the end of\nhis life bis Serius was actually tried\nfor treason and there were many times\nwhen Belisarius was on military campaign\nit was clear that Justinian was trying\nto sabotage him because obviously if\nyour Emperor you're afraid that uh your\ngeneral your great conquering General\nwill eventually come back and take your\nthrone okay so because of what happened\nbetween Justin and Blas basically this\nwas the last time that the bines uh\nembarked on a massive military\ncampaign okay from now on they're\ndefensive and also they focus on the\nidea of diplomacy basically bribing\ntheir enemies not to attack them\nespecially the Hunts uh but also the\nArabs as well as the Persian Empire\nokay this is the Hagia Sophia the\ncathedral to wisdom and this is the\ngreat Monument uh the great legacy of\nthe Byzantine Empire it's it's\nabsolutely beautiful again guys this is\nthis what's amazing it's still there\nokay you can actually get on a plane go\nto istano and visit this place it's\nactually it's absolutely gorgeous um\ndefinitely worth\nvisiting all right now why did constant\nconstant pole\nfall um and so what happened was that\nagain even though conle itself is\nimpenetrable it's\nInvincible um it's still it's still an\nEmpire and So eventually its regions\nwere eventually overrun by great enemies\nso for example in about the year 1450\nand this is 3 years before the eventual\nfall of the of the city uh the otoman\nEmpire just it's basically toen taken\nover the byzantines okay and the only\ncity left standing is constant pole okay\nso you can see over here are the\nOttomans over here is the Ottomans\nokay the Ottomans were able to conquer\nthe city because of the invention of\nSiege engines okay these are these\ncannons are as big big as houses and\nthey basically overwhelm the walls and\nallow the Ottomans to overrun the city\nnow what's important to understand is\neven though the bisan tees were\nChristian and the Ottomans were Muslim\nand even though uh the Turks overran the\ncity the Turks were extremely respectful\nto the citizens of the city because they\nwere considered the hearers the\nsuccessors to the Roman Empire uh and\nthis was the center of what we call the\nOrthodox church so the so so the\ncitizens were treated extremely well\nokay um this again is another picture of\nthe siege of constant all right let's\ntalk lastly\nabout um the significance and power of\nthe city the city was the center of the\nworld for hundreds of years but both\nintellectually because it again it was\nthe here to not just the Roman Empire\nbut also to Greek\ncivilization um it was also in terms of\ntrade the capital of the world because\nit was a meaning place of both the agian\nwhich leads to the Mediterranean as well\nas the Black Sea which leads into um\nwhat is Russia Today okay so if you\nwanted to go anywhere you basically had\nto go through Conant it was really a\ncenter of the world and through trade\ntaxing trade the city became extremely\nwealthy also because it was a center of\nthe world it was very Multicultural very\nCosmopolitan you had basically all major\nethnicities living inside the city Jews\nChristians Muslims were all treated with\nextreme\ntolerance they basically had their own\nquarters within the city okay as you can\nsee at its height the city was was\nextremely\nbeautiful and very wealthy it was really\nfor 100 years the capital of the world\nthe capital of the universe\nbasically um as you can see it is almost\nimpossible to besiege okay you you can\nnever cut it off from supplies you can\nnever isolate the city because it is the\nmeeting place of so many rivers okay\nthis is the\nbosor okay so that is the Roman Empire\nokay um so this is the again what we\nknow about it and now I'm going to\nexplain um my theory to these three\nquestions why did Constantine make the\nmove from Rome to bizantium why did it\nrise why did it de climb okay but before\nI start uh with my explanation are there\nany questions about what I just\npresented this is all pretty basic stuff\nthis is stuff you can find on the\ninternet uh um on Wikipedia you can ask\nchat GB I'll probably give you the same\nanswers okay but are there any questions\nso far about uh con Paul in the B Empire\nbefore I I I I present my\nideas was this clear to you\nguys any any questions\nguys maybe this is something you're\ncoming up to it is like shoot the\nquestion down but uh I I remember\nreading like in the early years of the\nthe Roman\nEmpire know Augustus\nTiberius so on Le culture there was GRE\nand like the\nemperor\nwriting Greek and all that kind of stuff\nand\nso like I I know move to Conant was a\ncouple hundred years after but was there\na certain cultural pull at the time were\ncertain Roman Elites feeling like they\nneed to be closer to like the core\nculture right okay that's a great\nquestion so culturally were the Romans\nat this time Greek or Roman um and\nyou're actually right duck in that Greek\nculture it's really the Hedon right I\nmean it's so many so much so Superior to\nRoman culture I mean Romans really were\npeasants uh who built an Empire but the\nGreeks uh basically built Western\nCivilization okay you had Homer you had\nPlato you had Herodotus the the Romans\nwere aware of this and this was a\nconflict within Roman culture\ncivilization for a long long time\nbecause they felt that even though they\nhad conquered the world they were about\nto be C conquered culturally by the\nGreeks so the Romans were aware of this\nand they rebelled against this and um\nyou weren't here for my lecture on the\ninad but really uh austa Caesar\nsponsored the writing of the indiat in\nresponse to the hemony of of Greek\nculture so even though you're right in\nthat most of the Roman aristocracy they\nEmbrace Greek culture uh such as like\nMark Anthony right uh Mark Anthony saw\nhimself as more Greek than than than\nRoman um there was a lot of push back\nfrom the empire against this okay so um\nbut eventually as we'll see eventually\nGreek culture does triumph all right so\nso so let me explain how all right so\nthe first question I want to look at is\nwhy did Constantine make the move\nfrom um Rome to Byzantium okay so let me\ngive you some\nbackground so um during the time of\nAugustus\nAugustus we we we today see him as the\nfirst Roman Emperor but we he do himself\nsee himself as the first emperor he just\nsaw himself as just a citizen of Rome\nokay he he is what we call a prin or he\ncall himself a PRP and this is where we\nget the um Modern English word Prince as\nwell as principal High School principal\nand it just means first first citizen so\nagain the problem with Rome is that you\nhad the aristocracy uh through the\nSenate monopolize all wealth and power\nand this led to a lot of contradictions\nand conflicts within the Roman Empire\nand so the\nsolution that Augustus proposed is make\nthe prinet make me the CEO okay this\nit's still committee it's still rule by\ncommittee but I'll be the coordinator\nI'll be the CEO okay and the idea here\nwas even though this was not a great\nsystem it did preserve the culture\nokay the history the Legacy uh and the\ntraditions of the Roman people and that\nwas what was important to protect and\npreserve the uh culture especially the\nidea of libertas okay\nLiberty um but this system didn't really\nwork right you had these Civil Wars you\nhad a lot of provincial um riots um\nRebellion so so this system simply\ndidn't work and this led to what we call\nthe crisis of the 3rd century when\nbasically the Roman Empire was about to\ncollapse okay and again as we said a a a\ngovernor a a commander named Diocletian\nhe saved the Roman Empire by reuniting\nokay and at this point he's like this\nsystem doesn't work what we need to do\nis study the Persian Empire because even\nthough we don't like the Persians their\ntheir empire seems a lot more\nsustainable and continuous than our\nEmpire okay and so this started a period\nwhat what we call the dominant okay\nbasically the idea of starting an\nimperial bureaucracy centralizing power\nuh with the emperor through the\nbureaucracy and the Romans hated this\nidea okay what what what emper\ndiscovered is this cultural\nshift um what the Romans just found AB\ndisgusting go back to the Assassin jul\nassassination of Julius Caesar\nright the the Romans are extremely\nculturally arrogant why did they\nassassinate Julius Caesar and the people\nwho assassinate Julius Caesar were his\nbest friends in fact we believe Marcus\nBrutus who was one of the lead\nconspirators was actually his biological\nson right why because Julius Caesar was\nthreatening the cultural traditions of\nRome they were afraid that Julius Caesar\nwould become king so what these Emperors\nuh first under Diocesan but especially\nunder Constantine discovered is it's\nreally hard to change culture and\nthere's really one solution to this\nproblem okay to understand this let's\nlet's run a thought experiment okay okay\nso you understand the percentage of\nculture okay so we're at at at school\nand this school is known for being\nInnovative it's being it's known for\nbeing student centered it focus a lot on\nactivities and extra curriculum right\nand that's great I'm very supportive of\nthis but let's just\nsay that uh the school brings me in as a\nconsultant and ask me to help improve\nthe school and I do lot I spend months\ninterviewing students and teachers I I\nfeel this school is great in terms of\ninnovation but it needs to focus more on\nacademics kids need to read more kids\nneed to focus more on um test scor\nand then you have a perfect balance okay\nand that's my solution well I'm pretty\nsure if I tried that um I'd be fired\nwithin a week okay and the reason why is\nI am attacking your cultural Traditions\nI'm attacking your identity your sense\nof self so if I want to implement my\nvision I can't force my vision on you\nthe only thing I can really do is switch\nschools and build my own school okay\ndoes that make sense you guys okay and\nthis is this is uh a pretty persistent\nuh thing throughout the world okay so\nthat's why\nConstantine made the move to Byzantium\nhe recognized that if I'm going to build\nan Empire and Rome needs to be an Empire\nif it is to\nendure I need to switch cultures and the\nbest way to switch culture is by moving\nyour capital from Rome to\nByzantium and when he did that\nthe entire culture shifted okay so so\nlet me very quickly explain the cultural\nshift in\nRome it was\nPagan okay oh by the way um Pagan is not\nthe word that they use okay Pagan is a\nword that Christians use to insult them\nbasically okay but but but for the sake\nof comedians we'll use the word Pagan uh\nthat was the religion they were Roman\nmeaning that they had a distinct\ncultural\nidentity and lastly they were Republic\nmeaning they were run by the Senate\nbasically okay not just Senate but by\ntradition and uh by custom\nokay by conole okay the basan empire was\ncompletely different first of all it was\nChristian and the Pagan and Christian\nworld view are in conflict with each\nother this is a major shift second is\nthey were\nMulticultural so as duck says um in the\ntime of Rome time of Augustus there was\na major conflict major debate uh between\nRoman culture and Greek culture but when\nthey switch switch over to conop pole\nthey completely Embrace Greek\nculture in fact the language switched\nfrom being Roman to Greek they spoke\nGreek and they embrac Greek culture\nHerodotus Plato uh were\nmajor thinkers that the that the um\nbasan Empire embraced and\ncelebrated and lastly it switched for me\nRepublic meaning that it went uh being\nrun by Senate to an\nEmpire which basically meant it was\nbeing run by a\nbureaucracy okay so bantine the bis\nEmpire is a very distinct enti from the\nRoman Empire historians today argue the\nbasian Empire is\ncontinuation of the ran Empire but\nthat's only a superficial and shallow\nunderstanding culturally the basian\nempire was a radical departure from the\nRoman Empire or the Roman Republic okay\nand so I will explain what these\ndifferences are and the and this it's be\nimportant because it's going to inform\nfor our understanding of future events\nin western civilization okay so let me\nfirst explain the difference in\nworldview between the Pagan and the\nChristian all\nright all right\nPagan and again guys I will have to make\na lot of\ngeneralizations but it's a useful\nframework for the understanding of um\nancient cultures okay so so what's the\nPagan worldview well in the Pagan\nworldview there are different lers to\nyour understanding of the world the\nforces the supernatural forces that you\ninteract with intimately are the\ngods okay and the gods is really a\nmetaphorical way to understand\nnature right so um in nature there are\nall these natural forces that we can't\nreally see for example the wind we can't\nreally see the wind but also we can't\nreally see creativity or luck well in\nthe Pagan worldview these hidden\ninvisible forces are rendered and\nexpressed as\nGods okay and the gods are those that we\ninteract with every day on an intimate\nbasis was very important for us to\nmaintain good relations with the gods by\nmaking ritual tributes to the gods okay\nso sacrifice and rituals were very\nimportant part of the Pagan worldview\nabove the Gods are actually even higher\ninvisible\nforces that no one has control of okay\nwhich this which includes fate which\nincludes luck okay Fortune okay but\nthere all there all but there are these\ninvisible forces that even the gods must\nsubmit to and then at the highest level\nare what are called um\nUnwritten and immutable immutable just\nmeans unable to change Eternal laws of\nthe universe and think of this structure\nas giving the universe some order and\nstructure okay so think of\ngravity right it's it's an Unwritten and\nIM inal law of the universe and what\nthey really mean by this is the idea\nreally of karma or Justice right if you\ndo good in the world good will happen to\nyou if you do evil in the world evil\nwill happen to to you it may not happen\nto you but it may happen to your\nchildren okay so there is a cosmic\nbalance to the world and this is really\nthe Pagan worldview\nright the Christian worldview is very\nsimple there's you okay you and then\nthere's God and the thing that matters\nis your personal relationship with God\nthat's it guys all right so let's look\nat the three major differ differences\nbetween the Pagan worldview and the\nChristian worldview okay and again this\nis a generalized simplified version and\nwe use it in order um to be clear about\nthe differences and that there are in\nfact differences all right so the three\nmajor differences are this the Christian\nworldview introduces into uh the Roman\nworld three ideas that really didn't\nexist before okay they are\ntruth evil\nand the\nindividual now these ideas actually\nexisted in other Traditions like the\nJewish tradition and the Persian\ntradition through Zionism but they\nreally didn't exist in the Greek and the\nRoman\ntradition so the counterpart to truth in\nthe Pagan tradition is the idea of um\nchaos or\nluck okay so there's no structure to the\nuniverse in the Christian worldview\nthere's a God who has designed the\nuniverse and that is the\ntruth okay so the intention of God is\nthe truth the plan is the truth whereas\nin the Pagan worldview there's no design\nguys it's just complete random chaos and\nyou just have to do try your best in\nthis world okay in the Christian\nworldview is the idea of evil which is\nif you go against the intention of God\nif you commit sin that is evil\nnow what's interesting for us is in the\nPagan worldview the opposite idea is\naction okay in other words in a word of\nchaos you have to act you have to do\nstuff if you refuse to act you are a\nslave so think back to the ilad right in\nin the ilad Achilles says why he is in\nTroy while he's fighting in Troy and he\nsays that before he came to\nTroy he was told his fate he could\neither\ndie\nold back at home or he could die young\nin\nTroy but by dying young in Troy he'll\nbecome famous he'll be remember forever\nand for Achilles that's not really a\nchoice what he's being told is you must\ncome to Troy and you\nmust die and that will win you eternal\nglory okay it's the idea of action also\nthink of the Romans okay in their\nLegends they have they have a name Nam\nmusas remember at the beginning of the\nRoman\nRepublic the Romans are besieged by the\natrian king and mushas is a young normal\nman only 20 years old he decides to\nassassinate the king in order to free\nthe Romans he swims across the Tyber and\nhe's about to do his deed but it's\npayday and the king is with his\nsecretary and they look alike they dress\nalike they look alike and Muses is\nhiding with his dagger and he knows it's\n5050 okay now for us we'd be like you\nknow what 50/50 is terrible odds so let\nme come back another day or let me be\nmore patient but for muus it's fortune\nfavors the Bold so he's like 50 is great\nit's great odds I'm never getting better\nodds so he takes his he takes his um dag\nand he kills the secretary okay he\nmisses then he's captured by The King\nThe King wants to torture him and force\nhim to confess and the King threats him\nand says I will burn you alive okay\nthere's a great fire beside musas if you\ndo not tell me the truth and what musas\ndoes is he puts his hand Into the Fire\nand lets it burn in front of the king\nand that scares the king okay that's the\nidea of action you make your fortune for\nyour\naction you cannot sit and wait you\ncannot deliberate you cannot be clever\nyou just act you're just Brave okay\nthat's a pagan worldview this is\nimportant for us because the um people\nwho will in feature in our course who's\nvery important and who follows worldview\nare also the Vikings okay so the Vikings\nshe the similar worldview it's a pagan\nworldview the last thing is the idea in\nthe Christian worldview it's an\nindividual that matters the individual",
      "claim_numbers": [
        3
      ]
    },
    {
      "slug": "pagan-christian-contrast",
      "label": "Pagan Christian Contrast",
      "body": "individual soul is what\nmatters okay but in the Pagan worldview\nwhat matters is the\ncommunity why are\nAchilles why is Achilles funny in Troy\nwhy is muus sacrificing himself for Rome\nbecause they want to remember by their\nCommunity all right so let me give you\ntwo examples of this let's go back to to\nthe ilad hector remember Hector Hector\nin Iliad he is the greatest Trojan\nWarrior and he's destroying the Greeks\nbecause Achilles refuses to\nfight but then Achilles um enters the\nbattlefield and at this point Hector's\nLieutenant tells him Hector Achilles is\nback let's go home let's go hide behind\nthe walls of Troy will be fine but\nHector says no fortune favors to bold\nthe gods are with me and so of course\nAchilles and the Greeks destroy the\nTrojans and they all have to and they're\nall forced to run back to the walls of\nTroy every Roman enters Troy except for\nHector Hector stays outside the walls of\nTroy and waits for Achilles to come he\nknows for a fact that Achilles will kill\nhim Achilles is a God\nhe's a great warrior but he's not a\nGod and at this point he knows he's\nabout to to be killed and most of us\nwould just sneak back into the walls of\nTroy right he can't do that because he's\nafraid of being um laughed at by his\nLieutenant he's afraid of Shame he has\nto die for his community okay so that's\nHector but also think about\nluria\nLua lucrecia remember is the woman Noble\nwoman who is raped by uh the son of uh\nTarquinius Superbus the last king of Rome\nand this is what starts the uh Rebellion\nthat uh overthrow the Roman\nmonarchy lucrecia is raped and then she\nkills\nherself because she's Dishonored and\nAugustine remember Augustine city of God\nhe writes about this okay and from his\nperspective it was a crime for Lucretia\nto kill herself why because we are all\nthe creation of God therefore we are the\nproperty of God therefore when we cure\nour when we kill ourselves we're\ncommitting um a sin against God we are\nbasically stealing from God and that's\nwhy if you commit suicide you'll be\ncondemned\nto Hell forever okay you'll be condemned\nto to damnation forever and then Austin\nexplains lucrecia killed herself because\nshe's afraid of the shame that she would\nhave to endure if she lived she was she\nwas afraid that she' be laughed at by\nThe Other Woman of of Rome okay and\nthat's the idea of community versus the\nindividual all right\nokay so um this so it's a radically\ndifferent worldview the Pagan versus the\nChristian let me explain some other\ndifferences for example the attitude\ntowards\nsex okay Christians because we live in a\nChristian world we know that sex is bad\nokay sex should only happen between\nhusband and wife and it should only\nhappen for the purpose of\nprocreation we shouldn't do it because\nwe enjoy it the pagans had the complete\nopposite attitude towards sex sex was to\nbe embraced it was to be enjoyed it was\nto be\ncelebrated why because if it if the gods\ndidn't mean for us to have sex they\nwouldn't make it so much fun okay so sex\nwas a very important part of pagan uh\nlife as well as violence okay they also\nembraced and celebrated violence so\nthink about the Vikings think about the\nRomans right they love violence and the\nChristians hated\nviolence\nso the argument is that the Christian\nworldview is an improvement on the Pagan\nworldview because the pagans they had\nthings like orgies they had things like\nchild sacrifice they had things like\ngenocide okay this is all bad\nright but remember and this is really\nimportant okay these are just two\ndifferent worldviews and it's hard for\nus to objectively assess which one is\nbetter we can only say that they both\nhave their benefits and they both have\ntheir uh\nconsequences okay an example is food if\nif we were to go to America today and\nlook at the food that Americans eat we\nbe discussed right hamburgers Coca-Cola\nfrench fries but guess what guys if if\nAmericans were to come to China they\nwould be equally disgusted by the food\nthat Chinese eat okay like malatang and\nand this stuff okay some of this stuff\nis really bad for you so I would keep\nthat in mind um it's easy for us to be\nculturally arrogant and say like we are\nso better than these\nancients but um it's all a matter of\nperspective if we were to go back in\ntime and look at the Pagan World we'd be\ndisgusted by the murderers by by the\nViolence by all the sex going on okay\nbut at the same time and this is really\nhard for us to understand but if they\nwere to come here there the time travel\nand come here and see our world they'd\nbe disgusted okay because like from\ntheir perspective we behave like\nslaves Achilles is out winning glory on\nthe beaches of Troy while we are in\nschool memorizing usess facts so that we\ncan get usess piece of Pap pieces of\npaper so that we can make useless pieces\nof money right of money is paper they\nwould not understand why we're doing\nthis to ourselves right so I would keep\nthat in mind like the Pagan worldview is\nvery different from the Christian\nworldview and that's it all right and in\nfact we will later in the semester\ndiscover that there are some thinkers\nsuch as nii Frederick nii who\nbelieve that the switch from the Pagan\nworldview to the Christian worldview was\na major setback M of civilization\nokay all right any questions about the\ndifference between the pagans and\nChristians before I move\non any\nquestions was this clear all right now\nlet's move on to the idea of republic\nversus\nEmpire okay and look I mean um the\ndifferences are pretty St AR right so in\na republic it's\nusually um there's there's like\negalitarianism okay everyone's opinion\ndoes\nmatter and in an\nEmpire there's a hierarchy okay so\nthat's the first major difference okay\nin a republic people are\negalitarian and in an Empire there's a\nhierarchy so think think about this in\nthe Persian Empire\num if you were to meet the emperor what\nyou have to do would what you have to do\nwas prostrate yourself first and then\nkiss his\nfeet all right that's the idea of Empire\nbut in the Republic you didn't do that\nin fact even though uh Rome was becoming\na welfare City a major tradition in Rome\nwas you didn't lock your doors you\ndidn't have guards so a senator who was\nin charge of go he was literally uh he\ncould literally put millions of people\nto death if he wanted to he didn't lock\nhis door so you the lonliest Roman could\njust walk into his house and have tea\nwith him or coffee with him and talk\nabout um life okay that was the\ntradition in Rome other also another\nthing is when Roman Senators walked the\nstreets of Rome they always carried an\numbrella something called a\num um yeah to protect themselves Okay\nthe reason why is this um Roman houses\nwere two\nstories and they didn't have switch\nsystem so if you need to go to the\nbathroom you did so using a bucket on\nthe second floor okay and so what\nhappened is if you saw someone you\ndidn't like walk the streets you would\nactually take your bucket and throw all\nthis at him okay that's literally\nwhat they did so if you're a senator um\nyou could be the most powerful man in\nthe world but you could still literally\nrisk having thrown at you okay so\nthat's the Roman world it was\negalitarian where's an Empire there's\nhierarchy so in the galarian world it\nmeans there's openness people are open\nto new ideas there's debate okay\nliterally anyone could propose a new\nidea whereas in the uh\nEmpire um it was very close system okay\nthey didn't like new ideas so go back to\nthe example of Greek fire right a guy\nand it's a story so we don't know if\nit's true but a guy had to go to the\nemperor and get his approval before the\nmilitary could adopt it that's really\ninefficient guys okay the Greeks would\nhave just gone and done it the Romans\nwould have would have let the commanders\nmake their own decisions it would not\nhappen the decision of the Senate it\nwould have been the decision of the\nmilitary commander that that was\nappointed by the Senate okay so um the\nthe Republic would be much more\nInnovative than the Empire because the\nRepublic would be much more open okay so\num there' be a lot more\ndiversity in a republic\nand in an Empire things would be much\nmore\nconformist okay you be you would have a\nlot more creativity a lot more diversity\nwithin a republic than Within an\nEmpire right and that's kind of\nintuitive because if you think about it\nan Empire has so much more people and so\nmuch more wealth and resources than a\nrepublic but at but historically we\nfound that republics and democracies are\nmuch more Innovative and creative than\nEmpires the reason has to do with the\nidea of a bureaucracy right something\nthat a democracy or\na republic does not have his idea of an\nimperial\nbureaucracy all right they have\nbureaucracies but they're not that big\nand they're not Imperial so let's talk\nabout\nbureaucracy right and this is a very\nimportant idea that I want you guys to\nremember for the rest of semester\nbecause we will refer to this idea right\nnow in the beginning bres are good for\nEmpires because because what they do is\nthey do centralization\nall right they're able\nto centralize the Empire unite the\nEmpire basically second thing that they\ndo that's important is the idea of\nsystemization all right basically keep\nrecords uh create laws systemization and\nlast is the idea of calization\nstandardization uniformity\nokay so getting people speak the same\nlanguage getting people to use the magic\nsystem um getting people to use money\nall right and this creates tremendous\nwealth within the empire in the early\nyears because again what you have is you\nhave the creation of\nmoney because you have a legal\nsystem and you have a\nmonopoly on\nviolence monopo mind just means that\nthese neighbors don't fight anymore okay\nbecause a police there are these courts\nthey can just Sue each other there's a\nlegal system and people are now using\nmoney um this leads to contracts and\nthis leads to trade and increased\neconomic\nactivity so you have peace and\nprosperity people feel safe uh people\nfeel that life is predictable so they do\nmore they work harder okay and this\nleads to in the early stages of Empire\nto\ntremendous\nProsperity okay\nbut over time what will happen is this\nbureaucracy will\naify meaning the people in within the\nbureaucracy will think of how to use the\nbureaucracy for their own personal\nbenefit okay we we we can say this is\ncorruption okay so centralization leads\nto corruption where just a minority\npeople with all the power use it for\ntheir own personal benefit they're\nbasically parasites the the technical\nword we use for this is rent seeking\nokay rent seeking so think of\nlandlords who charge rent to their\ntenants well if it's a monopoly they can\ncharge as much as they want there's\nnothing you can do about it okay it's\nwhat we call R seeking So centralization\neventually leads to\ncorruption systemization leads to\nultimately",
      "claim_numbers": [
        5
      ]
    },
    {
      "slug": "bureaucracy-stagnation",
      "label": "Bureaucracy Stagnation",
      "body": "stagnation okay there's nothing new\num going on and calization leads to the\nidea of Conformity or H homogenization\nokay where everything becomes the same\nwhere everything's this where everything\nis\nBland\nright does that make sense all\nright okay so why this happens\nis because even though the bureaucracy\nis only an institution among different\ninstitutions okay so think about this\nyou have the Imperial\nbureaucracy but they are compenent\nagainst the court system okay which is\nbasically Emperor okay and the court is\nusually controlled by Unix okay so these\nare Servants of the emperor the\nburocracy is up against the court it's\nalso up against the nobility right the\ntraditional power of society it's also\nup against the military\nit's also up against the\nchurch okay so there are\ndifferent um institutions that can\ncounter the bureaucracy but over time in\nterms of peace and prosperity if things\nare really stable eventually the\nbureaucracy triumphs over all these\nother\ninstitutions okay and the reason why is\nthis first is the y can\nmonopolize\nstatus okay and\nMobility so if you're just an ordinary\nperson well the best way to rise from\nour society is for the bureaucracy this\nis certainly true in China right where\nevery wants to be bureaucrat because\nthat's seen as the mechanism of\nachieving social status as well as\nsocial\nMobility\nalso proces\nmonopolize\ninformation it controls what information\nflows into the system it controls what\nthe emperor sees okay so we so we can\nsay this is about\ncensorship and\nsequency and the last thing that it does\nis monopolizes the idea of\nnarrative okay it it controls the\nproduction of\nculture and we\ncan uh so and it does this mainly\nthrough the process of writing history\nokay so remember history is the creation\nof a cultural narrative to bind people\ntogether and it's usually the Imperial\nbureaucrats who do this in other words\nwhat's important for us to understand is\nthe bureaucrats have a\nmonopoly of\nliteracy and\nknowledge they control the schools they\ncontrol the media they control history\nwriting they control how you think and\num\nwrite so even though these are they are\ncompeting institutions the bureaucracy\nby controlling this meta reality that's\nculture it controls the way like these\num other\ninstitutions behave okay so um the\nexample I want to use is the idea of the\ngodhead all right the\ngodhead so my argument to you is the\ngodhead it's really a bureaucratic\ninvention right because remember um in\nduring the C of NAIA NE neia there's a\ndebate as to the nature of Jesus there\nare these arens who believe that Jesus\nwas a lesser Divinity then there were\npeople called uh who believed in\nmodalism who who just believed the Holy\nSpirit Jesus and God were diff were\ndifferent forms of the same entity then\nyou have partialism which is say that\nthey are a part of the same entity okay\nand these three different explanations\nmake sense make they make intuitive\nsense the idea of the godhead where God\nJesus and the Holy\nSpirit are coequal separate but the same\nthing makes no\nsense and the reason why they would do\nthis is to create a sense of\nmystery right and distance\nand\nsecrecy and that my friends is a\ndefinition of a\nbureaucracy\nright I'm not sure if you de\nbureaucracies I have they suck they\ndehumanize you so think\nof I'll just use a silly example right\nso in America there's there's something\ncalled a census and on the census you\nhave to write down what racial group you\nbelong to and the racial group racial\ngroup I belong to if American is\nAsian-American right guess what guess\nwho else belongs in that group Indian\npeople Vietnamese people Japanese people\nKorean people that makes no sense we\nknow that in in uh Asia the Aeneidn\nculture is vastly different from the\nJapanese culture which is vastly\ndifferent from the Korean culture and\nthe Chinese culture and the vietamese\nculture okay these are different people\nwith their\nown uh belief systems but in a\nbureaucracy it just categorizes everyone\ntogether almost randomly or\nindifferently okay and that's why I I\nwould make the argument that ultimately\nMulticultural societies are not as\ncreative as as tribal\nsocieties okay tribal versus\nMulticultural think about the\nMulticultural societies that are are\naround us today okay sing Singapore is a\nMulticultural Society Canada is a\nMulticultural Society they're not very\ncreative guys they're very Bland they're\nvery\nconformist they're very\nbureaucratic\nokay very tribal societies like the\nGreeks the Greeks were extremely tribal\nthey were extremely s sistic they were\nextremely\ncreative right as\nwere um um as are the Europeans\nokay as are the\nVikings and the reason why is\ntribalism is energetic it makes you\npassionate it makes you think deeply\nabout the\nworld whereas in in a Multicultural\nSociety\npeople have to spend their energies\ngetting along with with with each other\nit's important not to be offensive okay\nand so it's because of these three uh\nreasons the certain the certain cultural\nconstruct of the banan Empire uh it was\nChristian it was\nMulticultural the word we can also use\nwe can also use is Cosmopolitan okay um\nalso it was bureaucratic the bisan tees\nwere not a very creative\npeople okay even though they had access\nto every culture in the world even\nthough they had access to the classics\nlike Plato Homer Herodotus as well as\nVirgil they were not that creative in\nfact if you had a genius like Homer or\nDante living in the bantin\nEmpire well he would just become a\nbureaucrat we would never know the\ngenius of Homer and Dante Homer and\nDante could only arise in tribal\nsocieties okay\nso that um yeah so does that make sense\nto you guys okay and again this is just\nan introduction to the conflict be\nbetween these political systems Empire\nversus republic bureaucracy versus um um\nyeah right we will continue uh these\nthemes and these topics as we uh move on\nthroughout um Western history but I I\nfirst want to introduce these ideas to\nyou it's really important that you\nunderstand the difference between\npaganism and Christianity because we'll\nbe referring uh to this conflict this\ndivision later on in the semester as\nwell any questions about\nthis please feel free to argue\nokay please feel free to ask questions\nto argue um because when you do that it\nhelps me improve my own\nthinking right any comments any\nfeedback okay so um I want I want to\ngive you some guys some time to think\nabout questions but before I do that I\nwant to I I want to look ahead over the\nnext couple weeks and tell you what\nwe'll be doing okay so we we did the\nRoman Empire then we did the byzantines\nso um as I explained to you the Roman\nEmpire\nuh Western Roman Empire will collapse in\nthe year\n476 when the last emperor uh ramus\nAugustus is the the PO\nokay but when he's the\npoed people don't understand the Roman\nEmpire has come to an\nend okay because um the people who are\nstill in charge think the Roman Empire\nis continuing but now we have a long\nperiod of Civil Wars throughout Europe\nall right and these civil wars were\neventually lead to something called the\nHoly Roman Empire which is something\nlike the uh which which is what\nCharlemagne or the Franks will create\nand this will lead interesting for us to\nthe to the rise of the\nVikings okay the Vikings are important\nbecause they will go on and\nbasically influence British culture as\nwell as Russian culture all right so\nRussia comes from the idea of the Rose\nokay the Roose are basically just\nVikings\num over here we will begin we will see\nthe beginning of the abased califit\nwhich is really the Golden Age of the um\nMuslims but eventually they'll be\nconquered by the\nMongols all right and the Congress of\nthe Mongols we eventually take us into\nthe Renaissance\nDante and this will Mark a be a new\nbeginning in world history okay so I I\njust want to explain to you what we what\nwhat we be doing we will definitely have\nto do um the Holy Roman Empire that's\nnumber one then this will lead us to the\nVikings number two then then we'll talk\nabout the abet caliphate number three\nand then we'll talk about the Mongols\nand then the Renaissance okay so this is\nwhat we doing over next two to three\nweeks right we'll be going very fast\nthroughout uh we'll be going very fast\nuh the semester okay so just let you\nknow all right",
      "claim_numbers": [
        6
      ]
    }
  ],
  "claims": [
    {
      "n": 1,
      "claim": "The lecture frames Byzantium as the continuation of the Roman Empire in the East.",
      "anchor": "byzantine-roman-continuation",
      "strength": "Explicit / Strong Implied",
      "confidence": "High"
    },
    {
      "n": 2,
      "claim": "The scholarly consensus is presented before Jiang offers a refuting interpretation.",
      "anchor": "scholarly-consensus-first",
      "strength": "Explicit / Strong Implied",
      "confidence": "High"
    },
    {
      "n": 3,
      "claim": "Constantinople's location, walls, sea access, and wealth explain part of Byzantine endurance.",
      "anchor": "theodosian-walls",
      "strength": "Explicit / Strong Implied",
      "confidence": "High"
    },
    {
      "n": 4,
      "claim": "Christianity and the Council of Nicaea are treated as central to Byzantine identity.",
      "anchor": "nicaea-trinity",
      "strength": "Explicit / Strong Implied",
      "confidence": "High"
    },
    {
      "n": 5,
      "claim": "The lecture contrasts pagan community, fate, and action with Christian individual soul, providence, and salvation.",
      "anchor": "pagan-christian-contrast",
      "strength": "Explicit / Strong Implied",
      "confidence": "High"
    },
    {
      "n": 6,
      "claim": "Bureaucracy is described as productive early and conformist or stagnant later.",
      "anchor": "bureaucracy-stagnation",
      "strength": "Explicit / Strong Implied",
      "confidence": "High"
    }
  ],
  "concepts": [],
  "layer1_summary": "The lecture asks why the Byzantine Empire exists, how it endured for more than a thousand years, and why it finally collapsed. Jiang first presents a conventional account: Constantine moved the capital east for strategic defense, access to wealthy provinces, and proximity to the Persian frontier.\n\nThe chapter then surveys Byzantine durability through Constantinople's geography, walls, sea defenses, Greek fire, the Hagia Sophia, Justinian, Belisarius, plague, and Ottoman conquest. It emphasizes the city as a center of trade, theology, and Roman-Greek inheritance.\n\nJiang then offers his own interpretation: Byzantium should be understood through Christianity, bureaucracy, multicultural cosmopolitanism, and the conversion of Roman republican energy into imperial administration. The lecture contrasts pagan and Christian worldviews and argues that bureaucracy first creates stability and prosperity, then hardens into conformity, censorship, and stagnation.",
  "paths": {
    "transcript": "lectures/civilization/civ-33/civ-33-transcript.md",
    "commentary": "lectures/civilization/civ-33/civ-33-commentary.md",
    "part_commentary": "",
    "part_bibliography": ""
  }
}
